clutter/__init__.py
clutter/scripts.py
clutter/aws/__init__.py
clutter/aws/common.py
clutter/aws/s3.py
clutter/aws/secrets_manager.py
clutter/aws/sqs.py
clutter/aws/ssm.py
clutter/aws/async/__init__.py
clutter/aws/async/s3.py
clutter/docker/__init__.py
clutter/docker/docker.py
clutter/logging/__init__.py
clutter/logging/logger.py
clutter/random/__init__.py
clutter/random/random.py
clutter/socket/__init__.py
clutter/socket/socket.py
clutter-2022.12.3.dist-info/LICENSE
clutter-2022.12.3.dist-info/METADATA
clutter-2022.12.3.dist-info/WHEEL
clutter-2022.12.3.dist-info/entry_points.txt
clutter-2022.12.3.dist-info/top_level.txt
clutter-2022.12.3.dist-info/RECORD
