Metadata-Version: 2.1
Name: clutter
Version: 2022.12.3
Summary: clutter
Author: Woojin Cho
Author-email: woojin.cho@gmail.com
Requires-Python: >=3.8
License-File: LICENSE
Requires-Dist: aioboto3
Requires-Dist: boto3
Requires-Dist: click
Requires-Dist: click-loglevel
Requires-Dist: tabulate
Requires-Dist: pendulum
Requires-Dist: pydantic
Requires-Dist: rich
